sifts/.gitignore
sifts/__init__.py
sifts/_version.py
sifts/core.py
sifts-1.2.0.dist-info/licenses/LICENSE
sifts-1.2.0.dist-info/METADATA
sifts-1.2.0.dist-info/WHEEL
sifts-1.2.0.dist-info/top_level.txt
sifts-1.2.0.dist-info/RECORD
