Metadata-Version: 2.4
Name: sifts
Version: 1.2.0
Summary: Simple full-text search library with SQL backend
Author-email: "David M. Straub" <straub@protonmail.com>
License: MIT
Project-URL: homepage, https://github.com/DavidMStraub/sifts
Project-URL: repository, https://github.com/DavidMStraub/sifts
License-File: LICENSE
Requires-Dist: SQLAlchemy
Requires-Dist: psycopg2-binary
Requires-Dist: numpy
Provides-Extra: testing
Requires-Dist: pytest; extra == "testing"
Requires-Dist: pytest-docker; extra == "testing"
Dynamic: license-file
